<?xml version="1.0" encoding="UTF-8" standalone="yes"?>

<GameTable>
  <map>
	<RegionBoard>
		<ScoreBonus>5</ScoreBonus>
		<regionName>Sea</regionName>
		<regionCities>
			<City>
				<name>Arkon</name>
				<region>Sea</region>
				<isKingPresent>false</isKingPresent>
				<CityColour>blue</CityColour>
				<nearCities>
					<City>Castrum</City>
					<City>Burgen</City>
				</nearCities>
			</City>
			<City>
				<name>Burgen</name>
				<region>Sea</region>
				<isKingPresent>false</isKingPresent>
				<CityColour>yellow</CityColour>
				<nearCities>
					<City>Arkon</City>
					<City>Dorful</City>
					<City>Esti</City>
				</nearCities>
			</City>
			<City>
				<name>Castrum</name>
				<region>Sea</region>
				<isKingPresent>false</isKingPresent>
				<CityColour>grey</CityColour>
				<nearCities>
					<City>Arkon</City>
					<City>Framek</City>
				</nearCities>
			</City>
			<City>
				<name>Dorful</name>
				<region>Sea</region>
				<isKingPresent>false</isKingPresent>
				<CityColour>gray</CityColour>
				<nearCities>
					<City>Burgen</City>
					<City>Graden</City>
				</nearCities>
			</City>
			<City>
				<name>Esti</name>
				<region>Sea</region>
				<isKingPresent>false</isKingPresent>
				<CityColour>orange</CityColour>
				<nearCities>
					<City>Burgen</City>
					<City>Hellar</City>
				</nearCities>
			</City>
		</regionCities>
		<PermitDeck>
			<PermitTile>
				<buildableCities>
					<buildableCity>A</buildableCity>
					<buildableCity>B</buildableCity>
				</buildableCities>
				<bonusSet>
					<AssistantBonus>1</AssistantBonus>
				</bonusSet>
			</PermitTile>
			<PermitTile>
			-------------------etc
			</PermitTile>
		</PermitDeck>
	</RegionBoard>
	<RegionBoard>
		<ScoreBonus>5</ScoreBonus>
		<regionName>Campaign</regionName>
		<regionCities>
			<City>
				<name>Framek</name>
				<region>Sea</region>
				<CityColour>blue</CityColour>
				<nearCities>
					<City>Castrum</City>
					<City>Burgen</City>
				</nearCities>
			</City>
			<City>
				<name>Graden</name>
				<region>Sea</region>
				<CityColour>yellow</CityColour>
				<nearCities>
					<City>Arkon</City>
					<City>Dorful</City>
					<City>Esti</City>
				</nearCities>
			</City>
			<City>
				<name>Hellar</name>
				<region>Sea</region>
				<CityColour>grey</CityColour>
				<nearCities>
					<City>Arkon</City>
					<City>Framek</City>
				</nearCities>
			</City>
			<City>
				<name>Indur</name>
				<region>Sea</region>
				<CityColour>gray</CityColour>
				<nearCities>
					<City>Burgen</City>
					<City>Graden</City>
				</nearCities>
			</City>
			<City>
				<name>Juvelar</name>
				<region>Sea</region>
				<CityColour>orange</CityColour>
				<nearCities>
					<City>Burgen</City>
					<City>Hellar</City>
				</nearCities>
			</City>
		</regionCities>
	</RegionBoard>
	<RegionBoard>
		<ScoreBonus>5</ScoreBonus>
		<name>Mountains</name>
		<regionCities>
			<City>
				<regionName>Arkon</regionName>
				<region>Sea</region>
				<CityColour>blue</CityColour>
				<nearCities>
					<City>Castrum</City>
					<City>Burgen</City>
				</nearCities>
			</City>
			<City>
				<name>Burgen</name>
				<region>Sea</region>
				<CityColour>yellow</CityColour>
				<nearCities>
					<City>Arkon</City>
					<City>Dorful</City>
					<City>Esti</City>
				</nearCities>
			</City>
			<City>
				<name>Castrum</name>
				<region>Sea</region>
				<CityColour>grey</CityColour>
				<nearCities>
					<City>Arkon</City>
					<City>Framek</City>
				</nearCities>
			</City>
			<City>
				<name>Dorful</name>
				<region>Sea</region>
				<CityColour>gray</CityColour>
				<nearCities>
					<City>Burgen</City>
					<City>Graden</City>
				</nearCities>
			</City>
			<City>
				<name>Esti</name>
				<region>Sea</region>
				<CityColour>orange</CityColour>
				<nearCities>
					<City>Burgen</City>
					<City>Hellar</City>
				</nearCities>
			</City>
		</regionCities>
	</RegionBoard>
  </map>	
	<NobilityTrack>
		<nobilityCells>
			<NobilityCell>
				<cellNumber>0</cellNumber>
				<BonusSet>
					<Bonus></Bonus>
				</BonusSet>
			</NobilityCell>
			<NobilityCell>
				<cellNumber>1</cellNumber>
				<BonusSet>
					<Bonus></Bonus>
				</BonusSet>
			</NobilityCell>
			<NobilityCell>
				<cellNumber>2</cellNumber>
				<BonusSet>
					<Bonus></Bonus>
				</BonusSet>
			</NobilityCell>
			<NobilityCell>
				<cellNumber>3</cellNumber>
				<BonusSet>
					<Bonus></Bonus>
				</BonusSet>
			</NobilityCell>
			-----------------------------------------
		</nobilityCells>
	</NobilityTrack>
	<kingRewardTiles>
		<ScoreBonus>25</ScoreBonus>
		<ScoreBonus>18</ScoreBonus>
		<ScoreBonus>12</ScoreBonus>
		<ScoreBonus>7</ScoreBonus>
		<ScoreBonus>3</ScoreBonus>
	</kingRewardTiles>
	<PoliticsDeck>
		<cardColours>
			<CardColour>white</CardColour>
			<CardColour>pink</CardColour>
			<CardColour>blue</CardColour>
			<CardColour>violet</CardColour>
			<CardColour>orange</CardColour>
			<CardColour>black</CardColour>
			<CardColour>rainbow</CardColour>
		</cardColours>
	</PoliticsDeck>
</GameTable>